feature_framework_api/README.md
feature_framework_api/__init__.py
it_feature_framework-0.0.0.dist-info/METADATA
it_feature_framework-0.0.0.dist-info/WHEEL
it_feature_framework-0.0.0.dist-info/RECORD
